duplicate_url_discarder/__init__.py
duplicate_url_discarder/_addon.py
duplicate_url_discarder/_fingerprinter.py
duplicate_url_discarder/pipelines.py
duplicate_url_discarder/py.typed
duplicate_url_discarder/rule.py
duplicate_url_discarder/url_canonicalizer.py
duplicate_url_discarder/utils.py
duplicate_url_discarder/processors/__init__.py
duplicate_url_discarder/processors/base.py
duplicate_url_discarder/processors/normalize.py
duplicate_url_discarder/processors/query_removal.py
duplicate_url_discarder/processors/query_removal_except.py
duplicate_url_discarder/processors/subpath_removal.py
duplicate_url_discarder-0.3.0.dist-info/LICENSE
duplicate_url_discarder-0.3.0.dist-info/METADATA
duplicate_url_discarder-0.3.0.dist-info/WHEEL
duplicate_url_discarder-0.3.0.dist-info/top_level.txt
duplicate_url_discarder-0.3.0.dist-info/RECORD
