Metadata-Version: 2.1
Name: duplicate-url-discarder
Version: 0.3.0
Summary: Discarding duplicate URLs based on rules.
Author-email: Zyte Group Ltd <info@zyte.com>
License: The MIT License (MIT)
Project-URL: Source, https://github.com/zytedata/duplicate-url-discarder
Classifier: Development Status :: 3 - Alpha
Classifier: Intended Audience :: Developers
Classifier: License :: OSI Approved :: BSD License
Classifier: Natural Language :: English
Classifier: Operating System :: OS Independent
Classifier: Programming Language :: Python :: 3
Classifier: Programming Language :: Python :: 3.9
Classifier: Programming Language :: Python :: 3.10
Classifier: Programming Language :: Python :: 3.11
Classifier: Programming Language :: Python :: 3.12
Classifier: Programming Language :: Python :: 3.13
Classifier: Programming Language :: Python :: Implementation :: CPython
Requires-Python: >=3.9
License-File: LICENSE
Requires-Dist: Scrapy>=2.11.0
Requires-Dist: url-matcher>=0.5.0
Requires-Dist: w3lib>=2.0.1
Provides-Extra: rules
Requires-Dist: duplicate-url-discarder-rules; extra == "rules"
